patchodon/__init__.py
patchodon/__main__.py
patchodon-0.1.0.dist-info/licenses/LICENSE
patchodon-0.1.0.dist-info/METADATA
patchodon-0.1.0.dist-info/WHEEL
patchodon-0.1.0.dist-info/entry_points.txt
patchodon-0.1.0.dist-info/top_level.txt
patchodon-0.1.0.dist-info/RECORD
