Metadata-Version: 2.4
Name: patchodon
Version: 0.1.0
Summary: Send and receive git patchsets via Mastodon
Author-email: Mirek Kratochvil <exa.exa@gmail.com>
License-Expression: GPL-3.0-or-later
Project-URL: Homepage, https://gitlab.com/exaexa/patchodon
Keywords: git,mastodon,patch
Classifier: Development Status :: 4 - Beta
Classifier: Intended Audience :: Science/Research
Classifier: Operating System :: POSIX
Classifier: Operating System :: Unix
Classifier: Programming Language :: Python :: 3
Classifier: Topic :: Communications
Classifier: Topic :: Software Development :: Version Control :: Git
Classifier: Topic :: Utilities
Requires-Python: >=3
License-File: LICENSE
Requires-Dist: requests>=2.25
Requires-Dist: html2text>=2025
Dynamic: license-file
